applied_biostats/__init__.py
applied_biostats/helpers.py
applied_biostats_helper-0.1.0.dist-info/METADATA
applied_biostats_helper-0.1.0.dist-info/WHEEL
applied_biostats_helper-0.1.0.dist-info/top_level.txt
applied_biostats_helper-0.1.0.dist-info/RECORD
