Metadata-Version: 2.1
Name: applied-biostats-helper
Version: 0.1.0
Summary: Helper package for Applied Biostats course - simplifies Colab environment setup and grading
Author-email: Applied Biostats Team <wnd22@drexel.edu>
License: MIT
Project-URL: Homepage, https://github.com/DamLabResources/applied-biostats-helper
Project-URL: Bug Reports, https://github.com/DamLabResources/applied-biostats-helper/issues
Project-URL: Source, https://github.com/DamLabResources/applied-biostats-helper
Keywords: education,biostats,jupyter,colab,grading
Classifier: Development Status :: 3 - Alpha
Classifier: Intended Audience :: Education
Classifier: License :: OSI Approved :: MIT License
Classifier: Operating System :: OS Independent
Classifier: Programming Language :: Python :: 3
Classifier: Programming Language :: Python :: 3.7
Classifier: Programming Language :: Python :: 3.8
Classifier: Programming Language :: Python :: 3.9
Classifier: Programming Language :: Python :: 3.10
Classifier: Programming Language :: Python :: 3.11
Classifier: Topic :: Education
Classifier: Topic :: Scientific/Engineering
Requires-Python: >=3.7
Requires-Dist: requests>=2.25.0
Requires-Dist: otter-grader==4.0.0
Requires-Dist: pingouin
Provides-Extra: dev
Requires-Dist: pytest>=6.0; extra == "dev"
Requires-Dist: black; extra == "dev"
Requires-Dist: flake8; extra == "dev"
Requires-Dist: twine; extra == "dev"
Requires-Dist: build; extra == "dev"
